[
    {
      "title": "ResearchGate",
      "description": "check out my papers",
      "accent": "papers",
      "accentType": "papers",
      "url": "https://www.researchgate.net/profile/Shunsuke-Ohtani?ev=hdr_xprf"
    },
    {
      "title": "GitHub",
      "description": "check out my codes",
      "accent": "codes",
      "accentType": "codes",
      "url": "https://github.com/kamikitanishun"
    },
    {
      "title": "SoundCloud",
      "description": "check out my tunes",
      "accent": "tunes",
      "accentType": "tunes",
      "url": "https://soundcloud.com/gk4tyrk70txe"
    }
  ]
  
