[
  {
    "rank": "1",
    "title": "どこまで変態になれますか?～ダウナー系マゾいじめサキュバスに『変態度を試される』レベル式オナサポ♡～",
    "url": "https://www.dlsite.com/maniax/work/=/product_id/RJ01525290.html"
  },
  {
    "rank": "2",
    "title": "✅早期限定特典付き【405分超】小悪魔カノジョ～からかいマゾいじり×あまあま恋人ムーブ⇒愛されまくり♡あなた好みのラブハメ交尾しまくる話～【マゾ度カスタム式音声】",
    "url": "https://www.dlsite.com/maniax/work/=/product_id/RJ01526921.html"
  },
  {
    "rank": "3",
    "title": "毒舌幼馴染み嫁メイドの純愛ご奉仕3",
    "url": "https://www.dlsite.com/maniax/work/=/product_id/RJ01533371.html"
  },
  {
    "rank": "4",
    "title": "妖艶な大人サキュバスの回数ノルマ式乳首オナサポ",
    "url": "https://www.dlsite.com/maniax/work/=/product_id/RJ01517863.html"
  },
  {
    "rank": "5",
    "title": "★1/22まで限定特典★妖艶な悪の女幹部の悪メス堕ち乳首責めエナジードレイン【わる～い女幹部が正義のヒーローを乳首開発しておめかし上手な悪メスヒーローに堕とす話】",
    "url": "https://www.dlsite.com/maniax/work/=/product_id/RJ01511075.html"
  },
  {
    "rank": "6",
    "title": "♡期間限定特典つき♡【4時間超え】性欲爆発♡秘書ドリームス",
    "url": "https://www.dlsite.com/maniax/work/=/product_id/RJ01532353.html"
  },
  {
    "rank": "7",
    "title": "【乳章I】プリ○リ乳牛物語  ～新春ニューイヤーミルク! 夢見る初搾り(ファースト・テイスティング)と白濁の海～",
    "url": "https://www.dlsite.com/maniax/work/=/product_id/RJ01530549.html"
  },
  {
    "rank": "8",
    "title": "【矛盾相反】あまあまマルチ催○ ～なすすべもなくイかされる極上の快楽～【全方向360°耳淫レ○プ】",
    "url": "https://www.dlsite.com/maniax/work/=/product_id/RJ01533584.html"
  },
  {
    "rank": "9",
    "title": "よわよわ先生 鶸村ひより～ASMR～",
    "url": "https://www.dlsite.com/maniax/work/=/product_id/RJ01495328.html"
  },
  {
    "rank": "10",
    "title": "【純度100%耳舐め音のみで作られたビート】堕液 ♯アナタを酩酊させるリズム耳舐めが快楽の沼に誘いオーガズムへ溺れる。【サウンドドラッグ】",
    "url": "https://www.dlsite.com/maniax/work/=/product_id/RJ01534423.html"
  }
]